gettimestamp/README.MD
gettimestamp/__init__.py
gettimestamp/requirements.txt
gettimestamp/thirdparty.json
gettimestamp-0.11.dist-info/LICENSE.rst
gettimestamp-0.11.dist-info/METADATA
gettimestamp-0.11.dist-info/WHEEL
gettimestamp-0.11.dist-info/top_level.txt
gettimestamp-0.11.dist-info/RECORD
