Metadata-Version: 2.1
Name: gettimestamp
Version: 0.11
Summary: A function to get a Timestamp string in the format YYYY_MM_DD_HH_MM_SS_microseconds ('_' can be defined)
Home-page: https://github.com/hansalemaos/gettimestamp
Author: Johannes Fischer
Author-email: aulasparticularesdealemaosp@gmail.com
License: MIT
Keywords: timestamp
Classifier: Development Status :: 4 - Beta
Classifier: Programming Language :: Python :: 3 :: Only
Classifier: Programming Language :: Python :: 3.10
Classifier: Topic :: Software Development :: Libraries :: Python Modules
Classifier: Topic :: Utilities
License-File: LICENSE.rst
